MANIFEST.in
MultipartPostHandler.py
README.txt
setup.cfg
setup.py
MultipartPostHandler2.egg-info/PKG-INFO
MultipartPostHandler2.egg-info/SOURCES.txt
MultipartPostHandler2.egg-info/dependency_links.txt
MultipartPostHandler2.egg-info/top_level.txt
examples/MultipartPostHandler-example.py