Metadata-Version: 1.1
Name: MultipartPostHandler2
Version: 0.1.4
Summary: A handler for urllib2 to enable multipart form uploading
Home-page: https://github.com/sergiomb2/MultipartPostHandler2/
Author: Sergio Basto
Author-email: sergio@serjux.com
License: LGPLv2.1+
Keywords: http,multipart,post,urllib2
Platform: UNKNOWN
Classifier: Programming Language :: Python
Classifier: Programming Language :: Python :: 2
Classifier: Development Status :: 4 - Beta
Classifier: Environment :: Other Environment
Classifier: Intended Audience :: Developers
Classifier: License :: OSI Approved :: GNU Library or Lesser General Public License (LGPL)
Classifier: Operating System :: OS Independent
Classifier: Topic :: Software Development :: Libraries :: Python Modules
